ingest/__init__.py
ingest/app.py
ingest/code_ingestion.py
ingest/detect.py
ingest/detect_setup.py
ingest/ingest.py
ingest/pdf_extractor.py
ingest/pdf_ingestion.py
ingest/postprocess_page.py
ingest/preprocess.py
ingest/preprocess_for_training.py
ingest/process_page.py
ingest/process_setup.py
ingest/schema.py
ingest/train_postprocess.py
ingest/process/__init__.py
ingest/process/app.py
ingest/process/detect.py
ingest/process/detection/__init__.py
ingest/process/detection/src/__init__.py
ingest/process/detection/src/detect.py
ingest/process/detection/src/infer.py
ingest/process/detection/src/model_builder.py
ingest/process/detection/src/preprocess.py
ingest/process/detection/src/update_annotations.py
ingest/process/detection/src/converters/__init__.py
ingest/process/detection/src/converters/html2xml.py
ingest/process/detection/src/converters/list2html.py
ingest/process/detection/src/converters/list2json.py
ingest/process/detection/src/converters/model2xml.py
ingest/process/detection/src/converters/pdf_extractor.py
ingest/process/detection/src/converters/xml2list.py
ingest/process/detection/src/evaluate/__init__.py
ingest/process/detection/src/evaluate/evaluate.py
ingest/process/detection/src/evaluate/evaluate_config.py
ingest/process/detection/src/evaluate/evaluate_iccv.py
ingest/process/detection/src/evaluate/evaluate_libs.py
ingest/process/detection/src/evaluate/ingestion.py
ingest/process/detection/src/tests/__init__.py
ingest/process/detection/src/tests/test_process_doc.py
ingest/process/detection/src/torch_model/__init__.py
ingest/process/detection/src/torch_model/inference/__init__.py
ingest/process/detection/src/torch_model/inference/inference.py
ingest/process/detection/src/torch_model/inference/data_layer/__init__.py
ingest/process/detection/src/torch_model/inference/data_layer/inference_loader.py
ingest/process/detection/src/torch_model/model/__init__.py
ingest/process/detection/src/torch_model/model/model.py
cosmos_ingest-0.1.dist-info/LICENSE
cosmos_ingest-0.1.dist-info/METADATA
cosmos_ingest-0.1.dist-info/WHEEL
cosmos_ingest-0.1.dist-info/top_level.txt
cosmos_ingest-0.1.dist-info/RECORD
